{"type": "Feature", "id": 12514807, "properties": {"woe:id": 12514807, "woe:parent_id": 1504946, "woe:name": "Selibabi Airport", "woe:placetype": 14, "woe:placetype_name": "Airport", "woe:lang": "ENG", "iso:country": "MR", "meta:provider": ["geoplanet:7.3.1", "geoplanet:7.3.2", "geoplanet:7.4.0", "geoplanet:7.4.1", "geoplanet:7.5.1", "geoplanet:7.5.2", "geoplanet:7.6.0", "geoplanet:7.8.1", "geoplanet:7.9.0", "geoplanet:7.10.0", "geoplanet:8.0.0", "woeplanet:8.0.0"], "meta:indexed": "2020-08-20T20:26:37.134417", "woe:alias_ENG_V": ["SEY Airport", "SEY"], "meta:updated": "2020-08-22T02:59:15.560986", "woe:hierarchy": {"continent": 24865670, "country": 23424896, "town": 0, "planet": 1, "county": 0, "suburb": 0, "state": 2346250, "region": 0, "localadmin": 0}, "woe:timezone_id": 28350724, "woe:hash": "edxq65zf9r0n", "woe:centroid": [-12.2061, 15.1822], "geom:latitude": 15.1822, "geom:longitude": -12.2061, "geom:hash": "edxq65zf9r0n", "woe:latitude": 15.1822, "geom:centroid": [-12.2061, 15.1822], "woe:longitude": -12.2061, "woe:repo": "woeplanet-airport-mr"}, "geometry": {"coordinates": [-12.2061, 15.1822], "type": "Point"}}